LICENSE
README.md
pyproject.toml
setup.py
exp_tracker.egg-info/PKG-INFO
exp_tracker.egg-info/SOURCES.txt
exp_tracker.egg-info/dependency_links.txt
exp_tracker.egg-info/requires.txt
exp_tracker.egg-info/top_level.txt
expense_tracker/__init__.py
expense_tracker/asgi.py
expense_tracker/settings.py
expense_tracker/urls.py
expense_tracker/wsgi.py
expenses/__init__.py
expenses/admin.py
expenses/apps.py
expenses/forms.py
expenses/models.py
expenses/tests.py
expenses/urls.py
expenses/views.py
expenses/migrations/0001_initial.py
expenses/migrations/0002_alter_expense_description.py
expenses/migrations/0003_alter_expense_description.py
expenses/migrations/__init__.py
expenses/templatetags/__init__.py
expenses/templatetags/custom_filters.py