Metadata-Version: 2.1
Name: exp-tracker
Version: 0.1.0
Summary: A python library project for managing personal expenses
Home-page: https://github.com/venkat2356/expense_tracker
Author: Venkata Ratnam Atyam
Author-email: x23291788@student.ncirl.ie
License: UNKNOWN
Platform: UNKNOWN
Classifier: Programming Language :: Python :: 3
Classifier: License :: OSI Approved :: MIT License
Classifier: Operating System :: OS Independent
Requires-Python: >=3.7
License-File: LICENSE
